Metadata-Version: 2.1
Name: airdrop
Version: 0.1.2
Summary: A package for automatically claiming airdrops.
Author: Shairul alim
Author-email: shairulalim644@gmail.com
Classifier: Programming Language :: Python :: 3
Classifier: License :: OSI Approved :: MIT License
Classifier: Operating System :: OS Independent
Requires-Python: >=3.6
License-File: LICENSE
Requires-Dist: colorama
Requires-Dist: requests
Requires-Dist: brotli
